setup.py
rush_serving/__init__.py
rush_serving/version.py
rush_serving.egg-info/PKG-INFO
rush_serving.egg-info/SOURCES.txt
rush_serving.egg-info/dependency_links.txt
rush_serving.egg-info/not-zip-safe
rush_serving.egg-info/requires.txt
rush_serving.egg-info/top_level.txt
rush_serving/api/__init__.py
rush_serving/api/rush_serving.py